Complex/__init__.py
Complex_Bidintha-0.7.dist-info/License.txt
Complex_Bidintha-0.7.dist-info/METADATA
Complex_Bidintha-0.7.dist-info/WHEEL
Complex_Bidintha-0.7.dist-info/top_level.txt
Complex_Bidintha-0.7.dist-info/RECORD
