Metadata-Version: 2.1
Name: Complex-Bidintha
Version: 0.7
Summary: Complex Numbers
Home-page: https://github.com/MrS0lver/Complex_Number
Author: Bidintha Machahry
Author-email: bidintha2006@gmail.com
License: License.txt
License-File: License.txt
